regexdict/__init__.py
regexdict/regexdict.py
Regex_Dict-0.1.0.dist-info/METADATA
Regex_Dict-0.1.0.dist-info/metadata.json
Regex_Dict-0.1.0.dist-info/DESCRIPTION.rst
Regex_Dict-0.1.0.dist-info/top_level.txt
Regex_Dict-0.1.0.dist-info/RECORD
Regex_Dict-0.1.0.dist-info/WHEEL
