Metadata-Version: 2.0
Name: Regex-Dict
Version: 0.1.0
Summary: A dict with sugar for regex searching over string keys.
Home-page: http://github.com/perimosocordiae/regexdict
Author: CJ Carey
Author-email: perimosocordiae@gmail.com
License: MIT
Platform: UNKNOWN
Classifier: Development Status :: 4 - Beta
Classifier: License :: OSI Approved :: MIT License
Classifier: Programming Language :: Python
